losshub/__init__.py
losshub/losses.py
losshub-0.0.6.dist-info/LICENSE
losshub-0.0.6.dist-info/METADATA
losshub-0.0.6.dist-info/WHEEL
losshub-0.0.6.dist-info/top_level.txt
losshub-0.0.6.dist-info/RECORD
