Metadata-Version: 2.1
Name: losshub
Version: 0.0.6
Summary: Classification Loss Function Library
Home-page: https://github.com/kadirnar/losshub
Author: kadirnar
License: MIT
Keywords: machine-learning,deep-learning,ml,pytorch,vision,loss,image-classification,video-classification
Classifier: Development Status :: 5 - Production/Stable
Classifier: Operating System :: OS Independent
Classifier: Intended Audience :: Developers
Classifier: Intended Audience :: Science/Research
Classifier: Programming Language :: Python :: 3
Classifier: Programming Language :: Python :: 3.7
Classifier: Programming Language :: Python :: 3.8
Classifier: Programming Language :: Python :: 3.9
Classifier: Topic :: Software Development :: Libraries
Classifier: Topic :: Software Development :: Libraries :: Python Modules
Classifier: Topic :: Education
Classifier: Topic :: Scientific/Engineering
Classifier: Topic :: Scientific/Engineering :: Artificial Intelligence
Requires-Python: >=3.7
License-File: LICENSE
Provides-Extra: dev
Requires-Dist: black (==21.7b0) ; extra == 'dev'
Requires-Dist: flake8 (==3.9.2) ; extra == 'dev'
Requires-Dist: isort (==5.9.2) ; extra == 'dev'
Provides-Extra: tests
Requires-Dist: black (==21.7b0) ; extra == 'tests'
Requires-Dist: flake8 (==3.9.2) ; extra == 'tests'
Requires-Dist: isort (==5.9.2) ; extra == 'tests'
